SavConverter/EditJson.py
SavConverter/JsonToSav.py
SavConverter/SavProperties.py
SavConverter/SavReader.py
SavConverter/SavToJson.py
SavConverter/SavWriter.py
SavConverter/__init__.py
SavConverter-0.1.1.dist-info/LICENSE
SavConverter-0.1.1.dist-info/METADATA
SavConverter-0.1.1.dist-info/WHEEL
SavConverter-0.1.1.dist-info/top_level.txt
SavConverter-0.1.1.dist-info/RECORD
