Metadata-Version: 2.1
Name: SavConverter
Version: 0.1.1
Summary: Python-GVAS-JSON-Converter (SavConverter) is a library designed to convert Unreal Engine's Game Variable and Attribute System (GVAS) files between .sav and .json formats.
Home-page: https://github.com/afkaf/Python-GVAS-JSON-Converter
Author: Ryan Grissett
Author-email: ryan.grissett@hotmail.com
License: Unlicense
Classifier: Intended Audience :: Developers
Classifier: Programming Language :: Python :: 3
License-File: LICENSE
